elf_inspector/__init__.py
elf_inspector/binary.py
elf_inspector/dwarf.py
elf_inspector/elf.py
elf_inspector/plugin_dwarf.py
elf_inspector/plugin_elf.py
elf_inspector-0.0.3.dist-info/AUTHORS.rst
elf_inspector-0.0.3.dist-info/CHANGELOG.rst
elf_inspector-0.0.3.dist-info/CODE_OF_CONDUCT.rst
elf_inspector-0.0.3.dist-info/METADATA
elf_inspector-0.0.3.dist-info/NOTICE
elf_inspector-0.0.3.dist-info/WHEEL
elf_inspector-0.0.3.dist-info/apache-2.0.LICENSE
elf_inspector-0.0.3.dist-info/entry_points.txt
elf_inspector-0.0.3.dist-info/top_level.txt
elf_inspector-0.0.3.dist-info/RECORD
